MANIFEST.in
README.md
setup.py
django_eel/__init__.py
django_eel/admin.py
django_eel/apps.py
django_eel/browsers.py
django_eel/chrome.py
django_eel/consumers.py
django_eel/models.py
django_eel/tests.py
django_eel/urls.py
django_eel/views.py
django_eel.egg-info/PKG-INFO
django_eel.egg-info/SOURCES.txt
django_eel.egg-info/dependency_links.txt
django_eel.egg-info/not-zip-safe
django_eel.egg-info/requires.txt
django_eel.egg-info/top_level.txt
django_eel/migrations/__init__.py
django_eel/static/eel/js/eel.js